chordgenerator/__init__.py
chordgenerator/forms.py
chordgenerator/urls.py
chordgenerator/views.py
chordgenerator/templates/chordgenerator/chordgenerator.html
chordgenerator/templatetags/__init__.py
chordgenerator/templatetags/musictags.py
chordgenerator-0.9.dist-info/LICENSE.txt
chordgenerator-0.9.dist-info/METADATA
chordgenerator-0.9.dist-info/WHEEL
chordgenerator-0.9.dist-info/top_level.txt
chordgenerator-0.9.dist-info/RECORD
