Metadata-Version: 2.1
Name: chordgenerator
Version: 0.9
Summary: A Django app for enumerating chords in a scale.
Home-page: http://pypi.python.org/pypi/chordgenerator/
Author: Peter Murphy
Author-email: peterkmurphy@gmail.com
License: LICENSE.txt
Keywords: music scale chords Django
Platform: UNKNOWN
Classifier: Development Status :: 4 - Beta
Classifier: Environment :: Other Environment
Classifier: Environment :: Web Environment
Classifier: Intended Audience :: Developers
Classifier: Intended Audience :: Education
Classifier: Intended Audience :: End Users/Desktop
Classifier: Intended Audience :: Other Audience
Classifier: License :: OSI Approved :: BSD License
Classifier: Programming Language :: Python
Classifier: Programming Language :: Python :: 2
Classifier: Operating System :: OS Independent
Classifier: Operating System :: MacOS
Classifier: Operating System :: Microsoft :: Windows
Classifier: Operating System :: POSIX
Classifier: Topic :: Artistic Software
Classifier: Topic :: Education
Classifier: Topic :: Multimedia :: Sound/Audio
Requires-Dist: Django (>=1.1.1)
Requires-Dist: musictheory (>=0.2)
